nlcontrol/__init__.py
nlcontrol/version.py
nlcontrol/closedloop/__init__.py
nlcontrol/closedloop/blocks.py
nlcontrol/closedloop/feedback.py
nlcontrol/signals/__init__.py
nlcontrol/signals/signal_constructors.py
nlcontrol/signals/signal_tools.py
nlcontrol/systems/__init__.py
nlcontrol/systems/eula.py
nlcontrol/systems/system.py
nlcontrol/systems/utils.py
nlcontrol/systems/controllers/__init__.py
nlcontrol/systems/controllers/basic.py
nlcontrol/systems/controllers/controller.py
nlcontrol/systems/controllers/eulaC.py
nlcontrol-1.0.3.dist-info/LICENSE
nlcontrol-1.0.3.dist-info/METADATA
nlcontrol-1.0.3.dist-info/WHEEL
nlcontrol-1.0.3.dist-info/top_level.txt
nlcontrol-1.0.3.dist-info/RECORD
